MANIFEST.in
README.txt
setup.cfg
setup.py
docs/HISTORY.txt
docs/INSTALL.txt
docs/LICENSE.GPL
docs/LICENSE.txt
ityou/__init__.py
ityou.ESI.egg-info/PKG-INFO
ityou.ESI.egg-info/SOURCES.txt
ityou.ESI.egg-info/dependency_links.txt
ityou.ESI.egg-info/entry_points.txt
ityou.ESI.egg-info/namespace_packages.txt
ityou.ESI.egg-info/not-zip-safe
ityou.ESI.egg-info/paster_plugins.txt
ityou.ESI.egg-info/requires.txt
ityou.ESI.egg-info/top_level.txt
ityou/ESI/__init__.py
ityou/ESI/configure.zcml
ityou/ESI/tests.py
ityou/ESI/profiles/default/metadata.xml
ityou/ESI/profiles/default/properties.xml
ityou/ESI/profiles/default/propertiestool.xml
ityou/ESI/profiles/default/workflows.xml
ityou/ESI/profiles/default/structure/.objects
ityou/ESI/profiles/default/structure/.preserve
ityou/ESI/profiles/default/structure/.workflow_states
ityou/ESI/profiles/default/structure/blog/.properties
ityou/ESI/profiles/default/structure/documents/.properties
ityou/ESI/profiles/default/structure/help/.properties
ityou/ESI/profiles/default/structure/web/.properties
ityou/ESI/profiles/default/structure/wiki/.properties
ityou/ESI/profiles/default/workflows/esi_intranet_folder_workflow/definition.xml
ityou/ESI/profiles/default/workflows/esi_intranet_workflow/definition.xml