Metadata-Version: 1.1
Name: ityou.ESI
Version: 1.3.1.0
Summary: ITYOU ESI - A Social Intranet Solution based on Plone
Home-page: http://www.ityou.de/esi
Author: ITYOU/LM
Author-email: lm@ityou.de
License: GPL
Keywords: Social Intranet,Plone,Activity Stream,Instant Messaging,Who is Online
Platform: UNKNOWN
Classifier: Framework :: Plone
Classifier: Programming Language :: Python
